Metadata-Version: 1.1
Name: django-imbue-tag
Version: 1.0
Summary: Django application containing special template tag that allows to inject template fragments into another template
Home-page: https://bitbucket.org/docsheet/django-imbue-tag/
Author: Piotr Olejarz
Author-email: d0csheet@protonmail.com
License: MIT
Platform: UNKNOWN
Classifier: Environment :: Web Environment
Classifier: Framework :: Django
Classifier: Framework :: Django :: 3.1
Classifier: Framework :: Django :: 3.0
Classifier: Framework :: Django :: 2.2
Classifier: Framework :: Django :: 2.1
Classifier: Framework :: Django :: 2.0
Classifier: Intended Audience :: Developers
Classifier: License :: OSI Approved :: MIT License
Classifier: Operating System :: OS Independent
Classifier: Programming Language :: Python
Classifier: Programming Language :: Python :: 3
Classifier: Topic :: Internet :: WWW/HTTP
Classifier: Topic :: Internet :: WWW/HTTP :: Dynamic Content
